telebaka_dravatar/__init__.py
telebaka_dravatar/admin.py
telebaka_dravatar/bot.py
telebaka_dravatar/models.py
telebaka_dravatar/preferences.py
telebaka_dravatar/migrations/0001_initial.py
telebaka_dravatar/migrations/__init__.py
telebaka_dravatar-0.1.1.dist-info/METADATA
telebaka_dravatar-0.1.1.dist-info/RECORD
telebaka_dravatar-0.1.1.dist-info/WHEEL
telebaka_dravatar-0.1.1.dist-info/top_level.txt
