Metadata-Version: 2.1
Name: telebaka-dravatar
Version: 0.1.1
Summary: UNKNOWN
Home-page: UNKNOWN
Author: bakatrouble
Author-email: bakatrouble@gmail.com
License: UNKNOWN
Platform: UNKNOWN
Requires-Dist: django
Requires-Dist: python-telegram-bot
Requires-Dist: Pillow
Requires-Dist: django-dynamic-preferences
